{
    "version": "1.11.0",
    "description": "A tool to validate the syntax of configuration files",
    "homepage": "https://boeing.github.io/config-file-validator/",
    "license": "Apache-2.0",
    "architecture": {
        "64bit": {
            "url": "https://github.com/Boeing/config-file-validator/releases/download/v1.11.0/validator-v1.11.0-windows-amd64.zip",
            "hash": "md5:0f5e03ace82779b81467ebb3437ffda5"
        },
        "32bit": {
            "url": "https://github.com/Boeing/config-file-validator/releases/download/v1.11.0/validator-v1.11.0-windows-386.zip",
            "hash": "md5:2b9b8adbc986161a917bb5cd75dcf8d3"
        }
    },
    "bin": "validator.exe",
    "checkver": {
        "github": "https://github.com/Boeing/config-file-validator"
    },
    "autoupdate": {
        "architecture": {
            "64bit": {
                "url": "https://github.com/Boeing/config-file-validator/releases/download/v$version/validator-v$version-windows-amd64.zip"
            },
            "32bit": {
                "url": "https://github.com/Boeing/config-file-validator/releases/download/v$version/validator-v$version-windows-386.zip"
            }
        },
        "hash": {
            "url": "$url.md5"
        }
    }
}
