{
    "version": "3.37.1",
    "description": "Spend more time programming. One command for an instant, secure URL to your localhost server through any NAT or firewall.",
    "homepage": "https://ngrok.com/",
    "license": {
        "identifier": "Shareware",
        "url": "https://ngrok.com/tos"
    },
    "notes": "There are breaking changes in v3 of ngrok. For details, see: https://ngrok.com/docs/guides/upgrade-v2-v3. To stay on v2, install versions/ngrok2",
    "architecture": {
        "64bit": {
            "url": "https://bin.equinox.io/a/mQJYv92vzty/ngrok-v3-3.37.1-windows-amd64.zip",
            "hash": "ff53d0913ae2dd4a49b9047a93c0fb838579a435af71cec35d4763170f960aab"
        },
        "32bit": {
            "url": "https://bin.equinox.io/a/gYBfv1o2WCS/ngrok-v3-3.37.1-windows-386.zip",
            "hash": "0d43cdfe047841a1ee998d6eba30e40510b5aa5a8983045b2c516218500e958f"
        }
    },
    "bin": "ngrok.exe",
    "checkver": {
        "url": "https://dl.equinox.io/ngrok/ngrok-v3/stable/archive",
        "regex": "/a/(?<hash64bit>\\w+)/ngrok-v[\\d.]+-([\\d.]+)-windows-amd64.zip(?:.|\\n)+?/a/(?<hash32bit>\\w+)/ngrok-v[\\d.]+-([\\d.]+)-windows-386.zip"
    },
    "autoupdate": {
        "architecture": {
            "64bit": {
                "url": "https://bin.equinox.io/a/$matchHash64bit/ngrok-v$majorVersion-$version-windows-amd64.zip"
            },
            "32bit": {
                "url": "https://bin.equinox.io/a/$matchHash32bit/ngrok-v$majorVersion-$version-windows-386.zip"
            }
        },
        "hash": {
            "url": "https://dl.equinox.io/ngrok/ngrok-v3/stable/archive",
            "regex": "$url(?:.|\\n)+?value=\"(\\w+)"
        }
    }
}
